CHANGELOG
README
extractnested.py
setup.py
nested.tar.archives.extractor.egg-info/PKG-INFO
nested.tar.archives.extractor.egg-info/SOURCES.txt
nested.tar.archives.extractor.egg-info/dependency_links.txt
nested.tar.archives.extractor.egg-info/top_level.txt