Metadata-Version: 1.0
Name: nested.tar.archives.extractor
Version: 1.1
Summary: A command line utility for recursively extracting nested tar archives.
Home-page: http://guanidene.blogspot.com/2011/06/nested-tar-archives-extractor.html
Author: Pushpak Dagade
Author-email: guanidene@gmail.com
License: UNKNOWN
Platform: Python 2.6 or 2.7.
